talus_utils/__init__.py
talus_utils/algorithms.py
talus_utils/apis.py
talus_utils/constants.py
talus_utils/dataframe.py
talus_utils/elib.py
talus_utils/fasta.py
talus_utils/plot.py
talus_utils/py.typed
talus_utils/s3.py
talus_utils/utils.py
talus_utils-0.1.6.dist-info/LICENSE.rst
talus_utils-0.1.6.dist-info/WHEEL
talus_utils-0.1.6.dist-info/METADATA
talus_utils-0.1.6.dist-info/RECORD
