Metadata-Version: 2.1
Name: talus-utils
Version: 0.1.6
Summary: Talus Utils
Home-page: https://github.com/rmeinl/talus-utils
License: MIT
Author: Rico Meinl
Author-email: rmeinl@talus.bio
Requires-Python: >=3.7.1,<4.0.0
Classifier: License :: OSI Approved :: MIT License
Classifier: Programming Language :: Python :: 3
Classifier: Programming Language :: Python :: 3.10
Classifier: Programming Language :: Python :: 3.7
Classifier: Programming Language :: Python :: 3.8
Classifier: Programming Language :: Python :: 3.9
Requires-Dist: boto3 (>=1.17.112,<2.0.0)
Requires-Dist: matplotlib-venn (>=0.11.6,<0.12.0)
Requires-Dist: pandas (>=1.3.0,<2.0.0)
Requires-Dist: plotly (>=5.1.0,<6.0.0)
Requires-Dist: pyarrow (>=4.0.1,<5.0.0)
Requires-Dist: toolz (>=0.11.1,<0.12.0)
Project-URL: Changelog, https://github.com/rmeinl/talus-utils/releases
Project-URL: Documentation, https://talus-utils.readthedocs.io
Project-URL: Repository, https://github.com/rmeinl/talus-utils
